nusugraph/__init__.py
nusugraph/main.py
nusugraph/test.py
nusugraph/utils.py
nusuGraph-2.1.dist-info/LICENSE
nusuGraph-2.1.dist-info/METADATA
nusuGraph-2.1.dist-info/WHEEL
nusuGraph-2.1.dist-info/top_level.txt
nusuGraph-2.1.dist-info/RECORD
