Metadata-Version: 2.1
Name: nusuGraph
Version: 2.1
Summary: An asynchronous and simplified Telegraph API Wrapper in Python
Home-page: https://github.com/Nusab19/nusuGraph
Download-URL: https://github.com/Nusab19/nusuGraph/archive/v2.1.zip
Author: Nusab Taha
Author-email: nusabtaha33@gmail.com
License: MIT
Classifier: License :: OSI Approved :: MIT License
Classifier: Operating System :: OS Independent
Classifier: Programming Language :: Python
Classifier: Programming Language :: Python :: 3
Classifier: Programming Language :: Python :: 3.6
Classifier: Programming Language :: Python :: 3.7
Classifier: Programming Language :: Python :: 3.8
Classifier: Programming Language :: Python :: 3.9
Classifier: Programming Language :: Python :: 3.10
Classifier: Programming Language :: Python :: 3.11
Classifier: Programming Language :: Python :: 3.12
License-File: LICENSE
Requires-Dist: httpx ==0.26.0
Requires-Dist: aiofiles ==23.2.1
